pynari-1.4.0.dist-info/RECORD
pynari-1.4.0.dist-info/WHEEL
pynari-1.4.0.dist-info/METADATA
pynari/libbarney.dylib
pynari/__init__.py
pynari/sample02.py
pynari/pynari.cpython-312-darwin.so
pynari/libanari.0.15.0.dylib
pynari/libanari_library_barney.dylib
pynari/libanari.0.dylib
